scikinC/BaseConverter.py
scikinC/ColumnTransformerConverter.py
scikinC/DecorrTransformerConverter.py
scikinC/FastQuantileLayerConverter.py
scikinC/FunctionTransformerConverter.py
scikinC/GBDTC_Converter.py
scikinC/GBDTTraversalConverter.py
scikinC/GBDTUnrollingConverter.py
scikinC/KerasSequentialConverter.py
scikinC/MinMaxScalerConverter.py
scikinC/ModelLoader.py
scikinC/PipelineConverter.py
scikinC/PolynomialFeaturesConverter.py
scikinC/QuantileTransformerConverter.py
scikinC/StandardScalerConverter.py
scikinC/__init__.py
scikinC/__main__.py
scikinC/_tools.py
scikinC/decorators.py
scikinC/layers/BaseLayerConverter.py
scikinC/layers/BatchNormalization.py
scikinC/layers/Dense.py
scikinC/layers/Dropout.py
scikinC/layers/LeakyReLU.py
scikinC/layers/PReLU.py
scikinC/layers/Softmax.py
scikinC/layers/__init__.py
scikinC/validation/MLFunction.py
scikinC/validation/__init__.py
scikinc-0.2.9.dist-info/licenses/LICENSE
scikinc-0.2.9.dist-info/METADATA
scikinc-0.2.9.dist-info/WHEEL
scikinc-0.2.9.dist-info/entry_points.txt
scikinc-0.2.9.dist-info/top_level.txt
scikinc-0.2.9.dist-info/RECORD
