Metadata-Version: 2.4
Name: scikinC
Version: 0.2.9
Summary: A converter for scikit learn and keras to hardcoded C function
Home-page: https://github.com/landerlini/scikinC
Author: Lucio Anderlini
Author-email: Lucio.Anderlini@fi.infn.it
Keywords: deployment,header-only,plain-C
Classifier: Development Status :: 3 - Alpha
Classifier: Intended Audience :: Developers
Classifier: Intended Audience :: Science/Research
Classifier: Topic :: Software Development :: Code Generators
Classifier: License :: OSI Approved :: MIT License
Classifier: Programming Language :: Python :: 3
Classifier: Programming Language :: Python :: 3.7
Classifier: Programming Language :: Python :: 3.8
Classifier: Programming Language :: Python :: 3.9
Classifier: Programming Language :: Python :: 3.10
Classifier: Programming Language :: Python :: 3.11
Classifier: Programming Language :: Python :: 3.12
Classifier: Programming Language :: Python :: 3.13
Classifier: Programming Language :: Python :: 3 :: Only
Requires-Python: >=3.6, <4
License-File: LICENSE
Requires-Dist: numpy
Requires-Dist: scipy
Requires-Dist: scikit-learn
Provides-Extra: keras
Requires-Dist: tensorflow; extra == "keras"
Requires-Dist: keras; extra == "keras"
Provides-Extra: fql
Requires-Dist: tensorflow; extra == "fql"
Requires-Dist: keras; extra == "fql"
Requires-Dist: fastquantilelayer; extra == "fql"
Dynamic: author
Dynamic: author-email
Dynamic: classifier
Dynamic: description
Dynamic: description-content-type
Dynamic: home-page
Dynamic: keywords
Dynamic: license-file
Dynamic: provides-extra
Dynamic: requires-dist
Dynamic: requires-python
Dynamic: summary
